spider_tools/__init__.py
spider_tools/file_utils.py
spider_tools/get_mysqldb.py
spider_tools/oss_manager.py
spider_tools/ragflow_manager.py
spider_tools/redis_manager.py
spider_tools/time_utils.py
spider_tools/utils.py
spider_tools_pro-0.0.2.dist-info/licenses/LICENSE
spider_tools_pro-0.0.2.dist-info/METADATA
spider_tools_pro-0.0.2.dist-info/WHEEL
spider_tools_pro-0.0.2.dist-info/entry_points.txt
spider_tools_pro-0.0.2.dist-info/top_level.txt
spider_tools_pro-0.0.2.dist-info/RECORD
