Metadata-Version: 2.4
Name: spider-tools-pro
Version: 0.0.2
Summary: A professional spider tools package
Home-page: https://github.com/6210qwe/spider_tool
Author: MindLullaby
Author-email: 3203939025@qq.com
Classifier: Development Status :: 3 - Alpha
Classifier: Intended Audience :: Developers
Classifier: Topic :: Software Development :: Libraries :: Python Modules
Classifier: Programming Language :: Python :: 3
Classifier: Programming Language :: Python :: 3.9
Classifier: Programming Language :: Python :: 3.10
Classifier: Programming Language :: Python :: 3.11
Classifier: License :: OSI Approved :: MIT License
Classifier: Operating System :: OS Independent
Classifier: Natural Language :: Chinese (Simplified)
Classifier: Framework :: Pytest
License-File: LICENSE
Requires-Dist: requests
Requires-Dist: lxml
Requires-Dist: loguru
Requires-Dist: urllib3
Requires-Dist: curl_cffi
Requires-Dist: aiomysql
Requires-Dist: aiohttp
Requires-Dist: click
Requires-Dist: html2text
Provides-Extra: dev
Requires-Dist: pytest; extra == "dev"
Requires-Dist: pytest-cov; extra == "dev"
Requires-Dist: black; extra == "dev"
Requires-Dist: isort; extra == "dev"
Requires-Dist: flake8; extra == "dev"
Requires-Dist: mypy; extra == "dev"
Provides-Extra: docs
Requires-Dist: sphinx; extra == "docs"
Requires-Dist: sphinx-rtd-theme; extra == "docs"
Dynamic: author
Dynamic: author-email
Dynamic: classifier
Dynamic: home-page
Dynamic: license-file
Dynamic: provides-extra
Dynamic: requires-dist
Dynamic: summary
